sec_downloader/__init__.py
sec_downloader/_modidx.py
sec_downloader/core.py
sec_downloader/download_storage.py
sec_downloader/sec_edgar_downloader_fork.py
sec_downloader/types.py
sec_downloader-0.12.2.dist-info/LICENSE
sec_downloader-0.12.2.dist-info/METADATA
sec_downloader-0.12.2.dist-info/WHEEL
sec_downloader-0.12.2.dist-info/entry_points.txt
sec_downloader-0.12.2.dist-info/top_level.txt
sec_downloader-0.12.2.dist-info/RECORD
