Metadata-Version: 2.1
Name: sec-downloader
Version: 0.12.2
Summary: Useful extensions for sec-edgar-downloader.
Home-page: https://github.com/Elijas/sec-downloader
Author: Elijas
Author-email: 4084885+Elijas@users.noreply.github.com
License: MIT License
Keywords: nbdev jupyter notebook python
Classifier: Development Status :: 4 - Beta
Classifier: Intended Audience :: Developers
Classifier: Natural Language :: English
Classifier: Programming Language :: Python :: 3.7
Classifier: Programming Language :: Python :: 3.8
Classifier: Programming Language :: Python :: 3.9
Classifier: Programming Language :: Python :: 3.10
Classifier: Programming Language :: Python :: 3.11
Classifier: Programming Language :: Python :: 3.12
Classifier: Programming Language :: Python :: 3.13
Classifier: Programming Language :: Python :: 3.14
Classifier: License :: OSI Approved :: MIT License
Requires-Python: >=3.7
Provides-Extra: dev
License-File: LICENSE
